{
  "id": "index",
  "title": "Home",
  "description": "Wave is an open-source terminal that adds the ability to launch graphical widgets, controlled and integrated directly with the CLI. We support MacOS, Linux, and Windows (Getting Started).",
  "source": "@site/docs/index.mdx",
  "sourceDirName": ".",
  "slug": "/",
  "permalink": "/docsite/",
  "draft": false,
  "unlisted": false,
  "tags": [],
  "version": "current",
  "sidebarPosition": -1,
  "frontMatter": {
    "sidebar_position": -1,
    "id": "index",
    "title": "Home",
    "hide_title": true,
    "hide_table_of_contents": true
  },
  "sidebar": "defaultSidebar",
  "next": {
    "title": "Getting Started",
    "permalink": "/docsite/gettingstarted"
  }
}